{
  payload: '{"ref":"refs/heads/master","before":"f8771ccc04d9ef93d13cb169041f1463d1931bdf","after":"0775f98ca70f5bc9874a3f166557bc4d5dd8a82b","repository":{"id":251075188,"node_id":"MDEwOlJlcG9zaXRvcnkyNTEwNzUxODg=","name":"eggs","full_name":"LloydPlayzHD/eggs","private":false,"owner":{"name":"LloydPlayzHD","email":"37116855+LloydPlayzHD@users.noreply.github.com","login":"LloydPlayzHD","id":37116855,"node_id":"MDQ6VXNlcjM3MTE2ODU1","avatar_url":"https://avatars.githubusercontent.com/u/37116855?v=4","gravatar_id":"","url":"https://api.github.com/users/LloydPlayzHD","html_url":"https://github.com/LloydPlayzHD","followers_url":"https://api.github.com/users/LloydPlayzHD/followers","following_url":"https://api.github.com/users/LloydPlayzHD/following{/other_user}","gists_url":"https://api.github.com/users/LloydPlayzHD/gists{/gist_id}","starred_url":"https://api.github.com/users/LloydPlayzHD/starred{/owner}{/repo}","subscriptions_url":"https://api.github.com/users/LloydPlayzHD/subscriptions","organizations_url":"https://api.github.com/users/LloydPlayzHD/orgs","repos_url":"https://api.github.com/users/LloydPlayzHD/repos","events_url":"https://api.github.com/users/LloydPlayzHD/events{/privacy}","received_events_url":"https://api.github.com/users/LloydPlayzHD/received_events","type":"User","site_admin":false},"html_url":"https://github.com/LloydPlayzHD/eggs","description":"edited pterodactyl eggs","fork":false,"url":"https://github.com/LloydPlayzHD/eggs","forks_url":"https://api.github.com/repos/LloydPlayzHD/eggs/forks","keys_url":"https://api.github.com/repos/LloydPlayzHD/eggs/keys{/key_id}","collaborators_url":"https://api.github.com/repos/LloydPlayzHD/eggs/collaborators{/collaborator}","teams_url":"https://api.github.com/repos/LloydPlayzHD/eggs/teams","hooks_url":"https://api.github.com/repos/LloydPlayzHD/eggs/hooks","issue_events_url":"https://api.github.com/repos/LloydPlayzHD/eggs/issues/events{/number}","events_url":"https://api.github.com/repos/LloydPlayzHD/eggs/events","assignees_url":"https://api.github.com/repos/LloydPlayzHD/eggs/assignees{/user}","branches_url":"https://api.github.com/repos/LloydPlayzHD/eggs/branches{/branch}","tags_url":"https://api.github.com/repos/LloydPlayzHD/eggs/tags","blobs_url":"https://api.github.com/repos/LloydPlayzHD/eggs/git/blobs{/sha}","git_tags_url":"https://api.github.com/repos/LloydPlayzHD/eggs/git/tags{/sha}","git_refs_url":"https://api.github.com/repos/LloydPlayzHD/eggs/git/refs{/sha}","trees_url":"https://api.github.com/repos/LloydPlayzHD/eggs/git/trees{/sha}","statuses_url":"https://api.github.com/repos/LloydPlayzHD/eggs/statuses/{sha}","languages_url":"https://api.github.com/repos/LloydPlayzHD/eggs/languages","stargazers_url":"https://api.github.com/repos/LloydPlayzHD/eggs/stargazers","contributors_url":"https://api.github.com/repos/LloydPlayzHD/eggs/contributors","subscribers_url":"https://api.github.com/repos/LloydPlayzHD/eggs/subscribers","subscription_url":"https://api.github.com/repos/LloydPlayzHD/eggs/subscription","commits_url":"https://api.github.com/repos/LloydPlayzHD/eggs/commits{/sha}","git_commits_url":"https://api.github.com/repos/LloydPlayzHD/eggs/git/commits{/sha}","comments_url":"https://api.github.com/repos/LloydPlayzHD/eggs/comments{/number}","issue_comment_url":"https://api.github.com/repos/LloydPlayzHD/eggs/issues/comments{/number}","contents_url":"https://api.github.com/repos/LloydPlayzHD/eggs/contents/{+path}","compare_url":"https://api.github.com/repos/LloydPlayzHD/eggs/compare/{base}...{head}","merges_url":"https://api.github.com/repos/LloydPlayzHD/eggs/merges","archive_url":"https://api.github.com/repos/LloydPlayzHD/eggs/{archive_format}{/ref}","downloads_url":"https://api.github.com/repos/LloydPlayzHD/eggs/downloads","issues_url":"https://api.github.com/repos/LloydPlayzHD/eggs/issues{/number}","pulls_url":"https://api.github.com/repos/LloydPlayzHD/eggs/pulls{/number}","milestones_url":"https://api.github.com/repos/LloydPlayzHD/eggs/milestones{/number}","notifications_url":"https://api.github.com/repos/LloydPlayzHD/eggs/notifications{?since,all,participating}","labels_url":"https://api.github.com/repos/LloydPlayzHD/eggs/labels{/name}","releases_url":"https://api.github.com/repos/LloydPlayzHD/eggs/releases{/id}","deployments_url":"https://api.github.com/repos/LloydPlayzHD/eggs/deployments","created_at":1585498380,"updated_at":"2021-05-09T15:50:47Z","pushed_at":1620575558,"git_url":"git://github.com/LloydPlayzHD/eggs.git","ssh_url":"git@github.com:LloydPlayzHD/eggs.git","clone_url":"https://github.com/LloydPlayzHD/eggs.git","svn_url":"https://github.com/LloydPlayzHD/eggs","homepage":null,"size":372764,"stargazers_count":5,"watchers_count":5,"language":null,"has_issues":true,"has_projects":true,"has_downloads":true,"has_wiki":true,"has_pages":false,"forks_count":15,"mirror_url":null,"archived":false,"disabled":false,"open_issues_count":0,"license":null,"forks":15,"open_issues":0,"watchers":5,"default_branch":"master","stargazers":5,"master_branch":"master"},"pusher":{"name":"LloydPlayzHD","email":"37116855+LloydPlayzHD@users.noreply.github.com"},"sender":{"login":"LloydPlayzHD","id":37116855,"node_id":"MDQ6VXNlcjM3MTE2ODU1","avatar_url":"https://avatars.githubusercontent.com/u/37116855?v=4","gravatar_id":"","url":"https://api.github.com/users/LloydPlayzHD","html_url":"https://github.com/LloydPlayzHD","followers_url":"https://api.github.com/users/LloydPlayzHD/followers","following_url":"https://api.github.com/users/LloydPlayzHD/following{/other_user}","gists_url":"https://api.github.com/users/LloydPlayzHD/gists{/gist_id}","starred_url":"https://api.github.com/users/LloydPlayzHD/starred{/owner}{/repo}","subscriptions_url":"https://api.github.com/users/LloydPlayzHD/subscriptions","organizations_url":"https://api.github.com/users/LloydPlayzHD/orgs","repos_url":"https://api.github.com/users/LloydPlayzHD/repos","events_url":"https://api.github.com/users/LloydPlayzHD/events{/privacy}","received_events_url":"https://api.github.com/users/LloydPlayzHD/received_events","type":"User","site_admin":false},"created":false,"deleted":false,"forced":false,"base_ref":null,"compare":"https://github.com/LloydPlayzHD/eggs/compare/f8771ccc04d9...0775f98ca70f","commits":[{"id":"0775f98ca70f5bc9874a3f166557bc4d5dd8a82b","tree_id":"37dd18f9c3d54170ed687dba246015cc97ac3cb4","distinct":true,"message":"Update version.txt","timestamp":"2021-05-09T16:52:38+01:00","url":"https://github.com/LloydPlayzHD/eggs/commit/0775f98ca70f5bc9874a3f166557bc4d5dd8a82b","author":{"name":"Lloyd","email":"37116855+LloydPlayzHD@users.noreply.github.com","username":"LloydPlayzHD"},"committer":{"name":"GitHub","email":"noreply@github.com","username":"web-flow"},"added":[],"removed":[],"modified":["version.txt"]}],"head_commit":{"id":"0775f98ca70f5bc9874a3f166557bc4d5dd8a82b","tree_id":"37dd18f9c3d54170ed687dba246015cc97ac3cb4","distinct":true,"message":"Update version.txt","timestamp":"2021-05-09T16:52:38+01:00","url":"https://github.com/LloydPlayzHD/eggs/commit/0775f98ca70f5bc9874a3f166557bc4d5dd8a82b","author":{"name":"Lloyd","email":"37116855+LloydPlayzHD@users.noreply.github.com","username":"LloydPlayzHD"},"committer":{"name":"GitHub","email":"noreply@github.com","username":"web-flow"},"added":[],"removed":[],"modified":["version.txt"]}}'
